[
  {
    "title": "Evolutionary Architecture Practices",
    "icon": "icon8.png",
    "content": "How systems can adapt over time"
  },
  {
    "title": "Responding to Change",
    "icon": "icon7.png",
    "content": "Design & Architecture practices to facilitate responding to change"
  },
  {
    "title": "Predicting Change",
    "icon": "icon2.png",
    "content": "Modelling & analysis techniques that enable predicting change"
  },
  {
    "title": "Socio-technical Systems Thinking",
    "icon": "icon1.png",
    "content": "Mitigate the risk and impact of unexpected change across the organisation"
  },
  {
    "title": "Novel Approaches",
    "icon": "icon5.png",
    "content": "Techniques that challenge 'best practice'"
  },
  {
    "title": "Case Studies",
    "icon": "icon3.png",
    "content": "Case studies, experience reports & retrospectives"
  }
]